watsonReport/__init__.py
watsonReport/watsonReport.py
WatsonReport-0.0.10.dist-info/METADATA
WatsonReport-0.0.10.dist-info/WHEEL
WatsonReport-0.0.10.dist-info/entry_points.txt
WatsonReport-0.0.10.dist-info/top_level.txt
WatsonReport-0.0.10.dist-info/RECORD
